{
	"animeName":"10_kougou",
	"percentageMax":"0.2",
	"totalFrame":"192",
	"width":"164",
	"height":"380",
	"headHeight":"205",
	"arrayFrame":[
		{"prop":"0,380,0,0"},
		{"prop":"0,380,0,0"},
		{"prop":"164,380,0,0"},
		{"prop":"164,380,0,0"},
		{"prop":"328,380,0,4"},
		{"prop":"328,380,0,4"},
		{"prop":"328,380,0,4"},
		{"prop":"492,380,0,4"},
		{"prop":"492,380,0,4"},
		{"prop":"656,380,0,8"},
		{"prop":"656,380,0,8"},
		{"prop":"656,380,0,8"},
		{"prop":"0,585,0,8"},
		{"prop":"0,585,0,8"},
		{"prop":"0,585,0,8"},
		{"prop":"0,585,0,8"},
		{"prop":"0,585,0,8"},
		{"prop":"164,585,0,0"},
		{"prop":"164,585,0,0"},
		{"prop":"328,585,0,0"},
		{"prop":"328,585,0,0"},
		{"prop":"328,585,0,0"},
		{"prop":"492,585,0,-4"},
		{"prop":"492,585,0,-3.05"},
		{"prop":"656,585,0,-2.25"},
		{"prop":"656,585,0,-1.55"},
		{"prop":"0,380,0,-1"},
		{"prop":"0,380,0,-0.55"},
		{"prop":"492,585,0,-0.25"},
		{"prop":"492,585,0,-0.05"},
		{"prop":"656,585,0,0"},
		{"prop":"656,585,0,0"},
		{"prop":"492,585,0,0"},
		{"prop":"492,585,0,0"},
		{"prop":"0,790,0,0"},
		{"prop":"0,790,0,0"},
		{"prop":"164,790,0,0"},
		{"prop":"164,790,0,0"},
		{"prop":"164,790,0,0"},
		{"prop":"328,790,0,0"},
		{"prop":"328,790,0,0"},
		{"prop":"328,790,0,0"},
		{"prop":"0,380,0,0"},
		{"prop":"0,380,0,0"},
		{"prop":"0,380,0,0"},
		{"prop":"0,380,0,0"},
		{"prop":"0,380,0,0"},
		{"prop":"0,380,0,0"},
		{"prop":"0,380,0,0"},
		{"prop":"492,790,0,0"},
		{"prop":"492,790,0,3"},
		{"prop":"164,380,0,3"},
		{"prop":"164,380,0,3"},
		{"prop":"164,380,0,3"},
		{"prop":"656,790,0,3"},
		{"prop":"656,790,0,7"},
		{"prop":"0,995,0,7"},
		{"prop":"0,995,0,7"},
		{"prop":"0,995,0,7"},
		{"prop":"164,995,0,7"},
		{"prop":"164,995,0,7"},
		{"prop":"164,995,0,7"},
		{"prop":"164,995,0,7"},
		{"prop":"164,585,0,7"},
		{"prop":"164,585,0,7"},
		{"prop":"164,585,0,7"},
		{"prop":"0,790,0,7"},
		{"prop":"0,790,-2,6"},
		{"prop":"0,790,-2,6"},
		{"prop":"164,585,-2,6"},
		{"prop":"164,585,-2,6"},
		{"prop":"164,585,-2,6"},
		{"prop":"0,790,2,3"},
		{"prop":"0,790,2,3"},
		{"prop":"0,380,2,3"},
		{"prop":"0,380,2,3"},
		{"prop":"0,380,2,3"},
		{"prop":"164,585,2,3"},
		{"prop":"164,585,2,3"},
		{"prop":"164,790,0,-3"},
		{"prop":"164,790,0,-1.35"},
		{"prop":"164,790,0,-0.35"},
		{"prop":"164,790,0,0"},
		{"prop":"328,995,0,0"},
		{"prop":"328,995,0,0"},
		{"prop":"164,380,0,0"},
		{"prop":"164,380,0,4"},
		{"prop":"656,790,0,4"},
		{"prop":"656,790,0,4"},
		{"prop":"656,790,0,-3"},
		{"prop":"328,380,0,-1.7"},
		{"prop":"328,380,0,-0.75"},
		{"prop":"328,380,0,-0.2"},
		{"prop":"0,380,0,0"},
		{"prop":"0,380,0,0"},
		{"prop":"0,380,0,0"},
		{"prop":"0,380,0,0"},
		{"prop":"0,380,0,0"},
		{"prop":"164,380,0,0"},
		{"prop":"164,380,0,0"},
		{"prop":"328,380,0,4"},
		{"prop":"328,380,0,4"},
		{"prop":"328,380,0,4"},
		{"prop":"492,380,0,4"},
		{"prop":"492,380,0,4"},
		{"prop":"656,380,0,8"},
		{"prop":"656,380,0,8"},
		{"prop":"656,380,0,8"},
		{"prop":"0,585,0,8"},
		{"prop":"0,585,0,8"},
		{"prop":"0,585,0,8"},
		{"prop":"0,585,0,8"},
		{"prop":"0,585,0,8"},
		{"prop":"164,585,0,0"},
		{"prop":"164,585,0,0"},
		{"prop":"328,585,0,0"},
		{"prop":"328,585,0,0"},
		{"prop":"328,585,0,0"},
		{"prop":"492,585,0,-4"},
		{"prop":"492,585,0,-3.05"},
		{"prop":"656,585,0,-2.25"},
		{"prop":"656,585,0,-1.55"},
		{"prop":"0,380,0,-1"},
		{"prop":"0,380,0,-0.55"},
		{"prop":"492,585,0,-0.25"},
		{"prop":"492,585,0,-0.05"},
		{"prop":"656,585,0,0"},
		{"prop":"656,585,0,0"},
		{"prop":"492,585,0,0"},
		{"prop":"492,585,0,0"},
		{"prop":"0,790,0,0"},
		{"prop":"0,790,0,0"},
		{"prop":"164,790,0,0"},
		{"prop":"164,790,0,0"},
		{"prop":"164,790,0,0"},
		{"prop":"328,790,0,0"},
		{"prop":"328,790,0,0"},
		{"prop":"328,790,0,0"},
		{"prop":"0,380,0,0"},
		{"prop":"0,380,0,0"},
		{"prop":"0,380,0,0"},
		{"prop":"0,380,0,0"},
		{"prop":"0,380,0,0"},
		{"prop":"0,380,0,0"},
		{"prop":"0,380,0,0"},
		{"prop":"492,790,0,0"},
		{"prop":"492,790,0,3"},
		{"prop":"164,380,0,3"},
		{"prop":"164,380,0,3"},
		{"prop":"164,380,0,3"},
		{"prop":"656,790,0,3"},
		{"prop":"656,790,0,7"},
		{"prop":"0,995,0,7"},
		{"prop":"0,995,0,7"},
		{"prop":"0,995,0,7"},
		{"prop":"164,995,0,7"},
		{"prop":"164,995,0,7"},
		{"prop":"164,995,0,7"},
		{"prop":"164,995,0,7"},
		{"prop":"164,585,0,7"},
		{"prop":"164,585,0,7"},
		{"prop":"164,585,0,7"},
		{"prop":"0,790,0,7"},
		{"prop":"0,790,-2,6"},
		{"prop":"0,790,-2,6"},
		{"prop":"164,585,-2,6"},
		{"prop":"164,585,-2,6"},
		{"prop":"164,585,-2,6"},
		{"prop":"0,790,2,3"},
		{"prop":"0,790,2,3"},
		{"prop":"0,380,2,3"},
		{"prop":"0,380,2,3"},
		{"prop":"0,380,2,3"},
		{"prop":"164,585,2,3"},
		{"prop":"164,585,2,3"},
		{"prop":"164,790,0,-3"},
		{"prop":"164,790,0,-1.35"},
		{"prop":"164,790,0,-0.35"},
		{"prop":"164,790,0,0"},
		{"prop":"328,995,0,0"},
		{"prop":"328,995,0,0"},
		{"prop":"164,380,0,0"},
		{"prop":"164,380,0,4"},
		{"prop":"656,790,0,4"},
		{"prop":"656,790,0,4"},
		{"prop":"656,790,0,-3"},
		{"prop":"328,380,0,-1.7"},
		{"prop":"328,380,0,-0.75"},
		{"prop":"328,380,0,-0.2"},
		{"prop":"0,380,0,0"},
		{"prop":"0,380,0,0"},
		{"prop":"0,380,0,0"}
	]
}